fluidly_generic_delete-0.1.1-py3.7-nspkg.pth
fluidly/generic_delete/__init__.py
fluidly/generic_delete/connection_delete.py
fluidly/generic_delete/py.typed
fluidly_generic_delete-0.1.1.dist-info/METADATA
fluidly_generic_delete-0.1.1.dist-info/WHEEL
fluidly_generic_delete-0.1.1.dist-info/namespace_packages.txt
fluidly_generic_delete-0.1.1.dist-info/top_level.txt
fluidly_generic_delete-0.1.1.dist-info/RECORD
